{
  "_class": "symbolInstance",
  "booleanOperation": -1,
  "clippingMaskMode": 0,
  "do_objectID": "D6DAB651-DB1E-4037-94F6-72D60F0A497C",
  "exportOptions": {
    "_class": "exportOptions",
    "do_objectID": "D8AA0BA0-D65E-4BE1-A28C-A65B66C17B9D",
    "exportFormats": [
    ],
    "includedLayerIds": [
    ],
    "layerOptions": 0,
    "shouldTrim": false
  },
  "frame": {
    "_class": "rect",
    "constrainProportions": false,
    "do_objectID": "D3772A92-1C34-41E9-A9D7-CC425DF44207",
    "height": 1,
    "width": 196,
    "x": 0,
    "y": 77
  },
  "hasClippingMask": false,
  "horizontalSpacing": 0,
  "isFixedToViewport": false,
  "isFlippedHorizontal": false,
  "isFlippedVertical": false,
  "isLocked": false,
  "isVisible": true,
  "layerListExpandedType": 0,
  "name": "Navigation / Left / Separation",
  "nameIsFixed": false,
  "overrideValues": [
  ],
  "resizingConstraint": 63,
  "resizingType": 0,
  "rotation": 0,
  "scale": 1,
  "shouldBreakMaskChain": false,
  "style": {
    "_class": "style",
    "do_objectID": "AAA4136D-75F6-4CCC-AFC0-DB9C5D66612B",
    "endMarkerType": 0,
    "miterLimit": 10,
    "startMarkerType": 0,
    "windingRule": 1
  },
  "symbolID": "46B00BF7-EDE7-4715-9FD2-EAC2061291A6",
  "verticalSpacing": 0
}