{
  "_class": "shapePath",
  "booleanOperation": -1,
  "clippingMaskMode": 0,
  "do_objectID": "B4482231-6747-492D-9773-CC9178181418",
  "edited": true,
  "exportOptions": {
    "_class": "exportOptions",
    "do_objectID": "27DCC362-7834-477B-BE59-E8AF2ADA3D70",
    "exportFormats": [
    ],
    "includedLayerIds": [
    ],
    "layerOptions": 0,
    "shouldTrim": false
  },
  "frame": {
    "_class": "rect",
    "constrainProportions": false,
    "do_objectID": "C031AEE6-7A29-4D6E-9B4D-222B26C0C992",
    "height": 1.163793103448278,
    "width": 3.270879310344828,
    "x": 56.60705172413776,
    "y": 275.3950603448275
  },
  "hasClippingMask": false,
  "isClosed": true,
  "isFixedToViewport": false,
  "isFlippedHorizontal": false,
  "isFlippedVertical": false,
  "isLocked": false,
  "isVisible": true,
  "layerListExpandedType": 0,
  "name": "Path",
  "nameIsFixed": false,
  "pointRadiusBehaviour": 1,
  "points": [
    {
      "_class": "curvePoint",
      "cornerRadius": 0,
      "curveFrom": "{0.8220978224773472, 0}",
      "curveMode": 4,
      "curveTo": "{0.92034726505052411, 0}",
      "hasCurveFrom": false,
      "hasCurveTo": true,
      "point": "{0.8220978224773472, 0}"
    },
    {
      "_class": "curvePoint",
      "cornerRadius": 0,
      "curveFrom": "{0.079652734949475848, 0}",
      "curveMode": 4,
      "curveTo": "{0.1779021775226528, 0}",
      "hasCurveFrom": true,
      "hasCurveTo": false,
      "point": "{0.1779021775226528, 0}"
    },
    {
      "_class": "curvePoint",
      "cornerRadius": 0,
      "curveFrom": "{0, 0.77613333333333301}",
      "curveMode": 2,
      "curveTo": "{0, 0.22386666666666694}",
      "hasCurveFrom": true,
      "hasCurveTo": true,
      "point": "{0, 0.5}"
    },
    {
      "_class": "curvePoint",
      "cornerRadius": 0,
      "curveFrom": "{0.1779021775226528, 1}",
      "curveMode": 4,
      "curveTo": "{0.079652734949475848, 1}",
      "hasCurveFrom": false,
      "hasCurveTo": true,
      "point": "{0.1779021775226528, 1}"
    },
    {
      "_class": "curvePoint",
      "cornerRadius": 0,
      "curveFrom": "{0.92034726505052411, 1}",
      "curveMode": 4,
      "curveTo": "{0.8220978224773472, 1}",
      "hasCurveFrom": true,
      "hasCurveTo": false,
      "point": "{0.8220978224773472, 1}"
    },
    {
      "_class": "curvePoint",
      "cornerRadius": 0,
      "curveFrom": "{1, 0.22386666666666694}",
      "curveMode": 2,
      "curveTo": "{1, 0.77613333333333301}",
      "hasCurveFrom": true,
      "hasCurveTo": true,
      "point": "{1, 0.5}"
    }
  ],
  "resizingConstraint": 63,
  "resizingType": 0,
  "rotation": 0,
  "shouldBreakMaskChain": false,
  "style": {
    "_class": "style",
    "do_objectID": "DF33FF8A-58E3-4755-AD5D-87D9E0D9A951",
    "endMarkerType": 0,
    "fills": [
      {
        "_class": "fill",
        "color": {
          "_class": "color",
          "alpha": 1,
          "blue": 0,
          "green": 0,
          "red": 0
        },
        "fillType": 0,
        "isEnabled": true,
        "noiseIndex": 0,
        "noiseIntensity": 0,
        "patternFillType": 1,
        "patternTileScale": 1
      }
    ],
    "miterLimit": 10,
    "startMarkerType": 0,
    "windingRule": 1
  }
}