{
  "_class": "symbolInstance",
  "booleanOperation": -1,
  "clippingMaskMode": 0,
  "do_objectID": "315BF626-3C22-49EF-A5AF-F9E9416D299C",
  "exportOptions": {
    "_class": "exportOptions",
    "do_objectID": "262184D1-3D0A-4C75-9954-BF62B063EDB4",
    "exportFormats": [
    ],
    "includedLayerIds": [
    ],
    "layerOptions": 0,
    "shouldTrim": false
  },
  "frame": {
    "_class": "rect",
    "constrainProportions": false,
    "do_objectID": "836DB794-1C24-42BA-B4DA-D9A0E0E86BF6",
    "height": 10,
    "width": 10,
    "x": 126,
    "y": 0
  },
  "hasClippingMask": false,
  "horizontalSpacing": 0,
  "isFixedToViewport": false,
  "isFlippedHorizontal": false,
  "isFlippedVertical": false,
  "isLocked": false,
  "isVisible": true,
  "layerListExpandedType": 0,
  "name": "Stations / Icons / X",
  "nameIsFixed": false,
  "overrideValues": [
  ],
  "resizingConstraint": 63,
  "resizingType": 0,
  "rotation": 0,
  "scale": 1,
  "shouldBreakMaskChain": false,
  "style": {
    "_class": "style",
    "do_objectID": "64F0C314-A96F-4692-A9F6-515FB285D372",
    "endMarkerType": 0,
    "miterLimit": 10,
    "startMarkerType": 0,
    "windingRule": 1
  },
  "symbolID": "8A044AFD-F8AE-44E1-BA0E-151EA0D7C8ED",
  "verticalSpacing": 0
}