{
  "_class": "group",
  "booleanOperation": -1,
  "clippingMaskMode": 0,
  "do_objectID": "D70DE2CD-016B-4BD0-87E0-B112616B197C",
  "exportOptions": {
    "_class": "exportOptions",
    "do_objectID": "1E56DF34-A3B0-4A1E-959A-147212C3D32F",
    "exportFormats": [
    ],
    "includedLayerIds": [
    ],
    "layerOptions": 0,
    "shouldTrim": false
  },
  "frame": {
    "_class": "rect",
    "constrainProportions": false,
    "do_objectID": "73477BF3-9CCE-4CFE-A185-F7CF7C028EC9",
    "height": 20,
    "width": 18,
    "x": 20,
    "y": 14
  },
  "hasClickThrough": false,
  "hasClippingMask": false,
  "isFixedToViewport": false,
  "isFlippedHorizontal": false,
  "isFlippedVertical": false,
  "isLocked": false,
  "isVisible": true,
  "layerListExpandedType": 1,
  "layers": [
    {
      "class": "shapePath",
      "id": "B229FE86-8997-4260-B92F-84BC747AD731"
    },
    {
      "class": "shapePath",
      "id": "44DECE86-C9C9-458C-A124-D4920DC891F5"
    }
  ],
  "name": "Group 2",
  "nameIsFixed": false,
  "resizingConstraint": 63,
  "resizingType": 0,
  "rotation": 0,
  "shouldBreakMaskChain": false,
  "style": {
    "_class": "style",
    "do_objectID": "8752DB83-5AEC-44C9-9E55-ADA43C5FFC98",
    "endMarkerType": 0,
    "miterLimit": 10,
    "startMarkerType": 0,
    "windingRule": 1
  }
}