{
  "_class": "symbolInstance",
  "booleanOperation": -1,
  "clippingMaskMode": 0,
  "do_objectID": "A0AF2678-2350-434D-9057-E67DDA976767",
  "exportOptions": {
    "_class": "exportOptions",
    "do_objectID": "BB0766D5-F9E1-46D1-9F41-294C22481BD1",
    "exportFormats": [
    ],
    "includedLayerIds": [
    ],
    "layerOptions": 0,
    "shouldTrim": false
  },
  "frame": {
    "_class": "rect",
    "constrainProportions": false,
    "do_objectID": "DC1BB55B-7F2E-46E5-A39C-BDAB5642A4FE",
    "height": 960,
    "width": 70,
    "x": 0,
    "y": 0
  },
  "hasClippingMask": false,
  "horizontalSpacing": 0,
  "isFixedToViewport": false,
  "isFlippedHorizontal": false,
  "isFlippedVertical": false,
  "isLocked": false,
  "isVisible": true,
  "layerListExpandedType": 0,
  "name": "Background",
  "nameIsFixed": true,
  "overrideValues": [
  ],
  "resizingConstraint": 63,
  "resizingType": 0,
  "rotation": 0,
  "scale": 1,
  "shouldBreakMaskChain": false,
  "style": {
    "_class": "style",
    "do_objectID": "6B7E7821-C43B-47B8-8AB6-94D6A7CAE773",
    "endMarkerType": 0,
    "miterLimit": 10,
    "startMarkerType": 0,
    "windingRule": 1
  },
  "symbolID": "5A118B52-632C-4ABF-82A8-E764B0536FAA",
  "verticalSpacing": 0
}