{
  "_class": "symbolInstance",
  "booleanOperation": -1,
  "clippingMaskMode": 0,
  "do_objectID": "733880FC-DF50-4CA8-A45F-4410599DAAC1",
  "exportOptions": {
    "_class": "exportOptions",
    "do_objectID": "653A4B15-8E14-44A2-99EC-77F1303D5684",
    "exportFormats": [
    ],
    "includedLayerIds": [
    ],
    "layerOptions": 0,
    "shouldTrim": false
  },
  "frame": {
    "_class": "rect",
    "constrainProportions": false,
    "do_objectID": "7643A337-01ED-4ADB-A81D-AC9B6D1A6816",
    "height": 70,
    "width": 70,
    "x": 0,
    "y": 78
  },
  "hasClippingMask": false,
  "horizontalSpacing": 0,
  "isFixedToViewport": false,
  "isFlippedHorizontal": false,
  "isFlippedVertical": false,
  "isLocked": false,
  "isVisible": true,
  "layerListExpandedType": 0,
  "name": "Dashboard",
  "nameIsFixed": true,
  "overrideValues": [
  ],
  "resizingConstraint": 63,
  "resizingType": 0,
  "rotation": 0,
  "scale": 1,
  "shouldBreakMaskChain": false,
  "style": {
    "_class": "style",
    "do_objectID": "6C9D5FA2-1CF6-4CAE-89AD-FA9AFBEA7955",
    "endMarkerType": 0,
    "miterLimit": 10,
    "startMarkerType": 0,
    "windingRule": 1
  },
  "symbolID": "138CF8CF-6C24-4DB2-A1AD-9C88811ECCB7",
  "verticalSpacing": 0
}