{
  "_class": "symbolInstance",
  "booleanOperation": -1,
  "clippingMaskMode": 0,
  "do_objectID": "ED4AA4E8-4004-4F1D-A074-131A3E786452",
  "exportOptions": {
    "_class": "exportOptions",
    "do_objectID": "22E8B9A7-0779-4FB1-9807-A9CCDE5F7C25",
    "exportFormats": [
    ],
    "includedLayerIds": [
    ],
    "layerOptions": 0,
    "shouldTrim": false
  },
  "frame": {
    "_class": "rect",
    "constrainProportions": false,
    "do_objectID": "B7C44FC4-E927-4CBF-8A37-3BDBA112D41A",
    "height": 47,
    "width": 254,
    "x": 701,
    "y": 1
  },
  "hasClippingMask": false,
  "horizontalSpacing": 0,
  "isFixedToViewport": false,
  "isFlippedHorizontal": false,
  "isFlippedVertical": false,
  "isLocked": false,
  "isVisible": true,
  "layerListExpandedType": 0,
  "name": "Performance Reporting / View / Graph Line",
  "nameIsFixed": false,
  "overrideValues": [
  ],
  "resizingConstraint": 63,
  "resizingType": 0,
  "rotation": 0,
  "scale": 1,
  "shouldBreakMaskChain": false,
  "style": {
    "_class": "style",
    "do_objectID": "63BA03A3-9E11-4ED2-93AF-D740C3B14058",
    "endMarkerType": 0,
    "miterLimit": 10,
    "startMarkerType": 0,
    "windingRule": 1
  },
  "symbolID": "EF00BAB2-CAA3-4F81-A268-7A763BC01F08",
  "verticalSpacing": 0
}