{
  "_class": "symbolInstance",
  "booleanOperation": -1,
  "clippingMaskMode": 0,
  "do_objectID": "D3D6669F-7CD1-414F-BED6-FEF6CECF57DA",
  "exportOptions": {
    "_class": "exportOptions",
    "do_objectID": "A9EEA053-533D-4A10-907C-CC67F73271ED",
    "exportFormats": [
    ],
    "includedLayerIds": [
    ],
    "layerOptions": 0,
    "shouldTrim": false
  },
  "frame": {
    "_class": "rect",
    "constrainProportions": false,
    "do_objectID": "50B59A3E-5E42-48EA-A012-695E8FB57225",
    "height": 44,
    "width": 44,
    "x": 0,
    "y": 25
  },
  "hasClippingMask": false,
  "horizontalSpacing": 0,
  "isFixedToViewport": false,
  "isFlippedHorizontal": false,
  "isFlippedVertical": false,
  "isLocked": false,
  "isVisible": true,
  "layerListExpandedType": 0,
  "name": "All",
  "nameIsFixed": true,
  "overrideValues": [
  ],
  "resizingConstraint": 63,
  "resizingType": 0,
  "rotation": 0,
  "scale": 1,
  "shouldBreakMaskChain": false,
  "style": {
    "_class": "style",
    "do_objectID": "2D93F473-2AB9-4A55-9E0E-392A2E6D6A41",
    "endMarkerType": 0,
    "miterLimit": 10,
    "startMarkerType": 0,
    "windingRule": 1
  },
  "symbolID": "7F09244E-0F80-40B2-9D63-4697608BDE01",
  "verticalSpacing": 0
}