{
  "_class": "symbolInstance",
  "booleanOperation": -1,
  "clippingMaskMode": 0,
  "do_objectID": "CDEF1DF7-1A8A-47C3-8D7A-B41A99555604",
  "exportOptions": {
    "_class": "exportOptions",
    "do_objectID": "A53B5478-202E-4C0B-A8CC-DD27EB1C3B6C",
    "exportFormats": [
    ],
    "includedLayerIds": [
    ],
    "layerOptions": 0,
    "shouldTrim": false
  },
  "frame": {
    "_class": "rect",
    "constrainProportions": false,
    "do_objectID": "D0FFA9CA-45D9-4F49-BEF9-16A648EEBC23",
    "height": 24,
    "width": 24,
    "x": 243,
    "y": 5
  },
  "hasClippingMask": false,
  "horizontalSpacing": 0,
  "isFixedToViewport": false,
  "isFlippedHorizontal": false,
  "isFlippedVertical": false,
  "isLocked": false,
  "isVisible": true,
  "layerListExpandedType": 0,
  "name": "Settings / Icons / + Active",
  "nameIsFixed": false,
  "overrideValues": [
  ],
  "resizingConstraint": 63,
  "resizingType": 0,
  "rotation": 0,
  "scale": 1,
  "shouldBreakMaskChain": false,
  "style": {
    "_class": "style",
    "do_objectID": "DCA60E0E-B5A7-421B-80E9-762B241D05D7",
    "endMarkerType": 0,
    "miterLimit": 10,
    "startMarkerType": 0,
    "windingRule": 1
  },
  "symbolID": "A1B71784-A158-4B82-93C4-CB9B6817F1AC",
  "verticalSpacing": 0
}