{
  "_class": "symbolInstance",
  "booleanOperation": -1,
  "clippingMaskMode": 0,
  "do_objectID": "3A8FD721-8FA1-4BF7-B7A0-7292732C2859",
  "exportOptions": {
    "_class": "exportOptions",
    "do_objectID": "1469958E-BBE7-446A-8CA3-B0B0E96C5BD6",
    "exportFormats": [
    ],
    "includedLayerIds": [
    ],
    "layerOptions": 0,
    "shouldTrim": false
  },
  "frame": {
    "_class": "rect",
    "constrainProportions": false,
    "do_objectID": "A5C41A0B-CDFC-4354-8734-DB04738AFFFA",
    "height": 1,
    "width": 260,
    "x": 0,
    "y": 70
  },
  "hasClippingMask": false,
  "horizontalSpacing": 0,
  "isFixedToViewport": false,
  "isFlippedHorizontal": false,
  "isFlippedVertical": false,
  "isLocked": false,
  "isVisible": true,
  "layerListExpandedType": 0,
  "name": "Separation",
  "nameIsFixed": true,
  "overrideValues": [
  ],
  "resizingConstraint": 63,
  "resizingType": 0,
  "rotation": 0,
  "scale": 1,
  "shouldBreakMaskChain": false,
  "style": {
    "_class": "style",
    "do_objectID": "4F27BAFA-E042-40C4-8546-2D7934CFAE66",
    "endMarkerType": 0,
    "miterLimit": 10,
    "startMarkerType": 0,
    "windingRule": 1
  },
  "symbolID": "37128A2E-9738-4D3F-BE39-F406BDE1600E",
  "verticalSpacing": 0
}