{
  "_class": "group",
  "booleanOperation": -1,
  "clippingMaskMode": 0,
  "do_objectID": "5FB8F3D3-2DE8-49E5-9392-1B21B56F7170",
  "exportOptions": {
    "_class": "exportOptions",
    "do_objectID": "26815065-CEB0-49EA-9739-91314B688C9B",
    "exportFormats": [
    ],
    "includedLayerIds": [
    ],
    "layerOptions": 0,
    "shouldTrim": false
  },
  "frame": {
    "_class": "rect",
    "constrainProportions": false,
    "do_objectID": "67CE2D5D-C19F-434F-B837-8724E55A3012",
    "height": 19,
    "width": 89,
    "x": 144,
    "y": 7.5
  },
  "hasClickThrough": false,
  "hasClippingMask": false,
  "isFixedToViewport": false,
  "isFlippedHorizontal": false,
  "isFlippedVertical": false,
  "isLocked": false,
  "isVisible": true,
  "layerListExpandedType": 0,
  "layers": [
    {
      "class": "symbolInstance",
      "id": "815BA4BD-BC45-4617-90EA-33CAAD68DED9"
    }
  ],
  "name": "Group 2",
  "nameIsFixed": false,
  "resizingConstraint": 63,
  "resizingType": 0,
  "rotation": 0,
  "shouldBreakMaskChain": false,
  "style": {
    "_class": "style",
    "do_objectID": "8222D1CE-6C81-4FC8-8414-2B6972B0735E",
    "endMarkerType": 0,
    "miterLimit": 10,
    "startMarkerType": 0,
    "windingRule": 1
  }
}