{
  "_class": "symbolInstance",
  "booleanOperation": -1,
  "clippingMaskMode": 0,
  "do_objectID": "24FEFA9E-75EC-4BE9-B369-103A64D430C6",
  "exportOptions": {
    "_class": "exportOptions",
    "do_objectID": "058A44A1-B75C-48EE-97F3-21A60DA54383",
    "exportFormats": [
    ],
    "includedLayerIds": [
    ],
    "layerOptions": 0,
    "shouldTrim": false
  },
  "frame": {
    "_class": "rect",
    "constrainProportions": false,
    "do_objectID": "C84386C4-A2CB-4EB9-9E03-F02694F245CE",
    "height": 70,
    "width": 196,
    "x": 0,
    "y": 78
  },
  "hasClippingMask": false,
  "horizontalSpacing": 0,
  "isFixedToViewport": false,
  "isFlippedHorizontal": false,
  "isFlippedVertical": false,
  "isLocked": false,
  "isVisible": true,
  "layerListExpandedType": 0,
  "name": "Navigation / Left / Components / Menu Item 1",
  "nameIsFixed": true,
  "overrideValues": [
  ],
  "resizingConstraint": 63,
  "resizingType": 0,
  "rotation": 0,
  "scale": 1,
  "shouldBreakMaskChain": false,
  "style": {
    "_class": "style",
    "do_objectID": "E66C3819-2320-432B-8B4F-3041EE7B6BA4",
    "endMarkerType": 0,
    "miterLimit": 10,
    "startMarkerType": 0,
    "windingRule": 1
  },
  "symbolID": "7A3D2AF3-A286-46DE-8027-4ABA6E28E32B",
  "verticalSpacing": 0
}