{
  "_class": "text",
  "attributedString": {
    "_class": "attributedString",
    "attributes": [
      {
        "_class": "stringAttribute",
        "attributes": {
          "MSAttributedStringColorAttribute": {
            "_class": "color",
            "alpha": 1,
            "blue": 0.5510469812925171,
            "green": 0.5510469812925171,
            "red": 0.5510469812925171
          },
          "MSAttributedStringFontAttribute": {
            "_class": "fontDescriptor",
            "attributes": {
              "name": "SanFranciscoDisplay-Regular",
              "size": 16
            }
          },
          "kerning": 0.1002337,
          "paragraphStyle": {
            "_class": "paragraphStyle",
            "maximumLineHeight": 16,
            "minimumLineHeight": 16
          }
        },
        "length": 21,
        "location": 0
      }
    ],
    "string": "PERFORMANCE REPORTING"
  },
  "automaticallyDrawOnUnderlyingPath": false,
  "booleanOperation": 0,
  "clippingMaskMode": 0,
  "do_objectID": "FDADE5B3-B55A-40BF-8A14-DA1F8736F74B",
  "dontSynchroniseWithSymbol": false,
  "exportOptions": {
    "_class": "exportOptions",
    "do_objectID": "CEAAB74A-CCBE-407B-9C55-991FEF2C2A8E",
    "exportFormats": [
    ],
    "includedLayerIds": [
    ],
    "layerOptions": 0,
    "shouldTrim": false
  },
  "frame": {
    "_class": "rect",
    "constrainProportions": false,
    "do_objectID": "34F8D629-812F-4C62-B7BF-89424061C8F4",
    "height": 16,
    "width": 190,
    "x": 30,
    "y": 24.5
  },
  "glyphBounds": "{{1, 3}, {188, 12}}",
  "hasClippingMask": false,
  "isFixedToViewport": false,
  "isFlippedHorizontal": false,
  "isFlippedVertical": false,
  "isLocked": false,
  "isVisible": true,
  "layerListExpandedType": 0,
  "lineSpacingBehaviour": 2,
  "name": "Module Title",
  "nameIsFixed": true,
  "resizingConstraint": 11,
  "resizingType": 0,
  "rotation": 0,
  "shouldBreakMaskChain": false,
  "style": {
    "_class": "style",
    "do_objectID": "C4655F3D-6B35-47E0-B48B-7E6E3D3F636C",
    "endMarkerType": 0,
    "miterLimit": 10,
    "startMarkerType": 0,
    "textStyle": {
      "_class": "textStyle",
      "do_objectID": "F261D884-2F1E-4E69-AF6E-32983346C424",
      "encodedAttributes": {
        "MSAttributedStringColorAttribute": {
          "_class": "color",
          "alpha": 1,
          "blue": 0.5510469812925171,
          "green": 0.5510469812925171,
          "red": 0.5510469812925171
        },
        "MSAttributedStringFontAttribute": {
          "_class": "fontDescriptor",
          "attributes": {
            "name": "SanFranciscoDisplay-Regular",
            "size": 16
          }
        },
        "kerning": 0.1002337,
        "paragraphStyle": {
          "_class": "paragraphStyle",
          "maximumLineHeight": 16,
          "minimumLineHeight": 16
        }
      },
      "verticalAlignment": 0
    },
    "windingRule": 1
  },
  "textBehaviour": 0
}